{

    "name": "Susanne Westerberg",
    "experiences": [

      {
        "title": "Paint",
        "description": "Lorem ipsum dolor sit amet, consectetur adipisicing elit. Cumque con Reiciendis?"
      },
      {
        "title": "Paint",
        "description": "Lore elit. Cumque consequatur optio architecto voluptatibus nesciunt. Reiciendis?"
      },
      {
        "title": "Paint",
        "description": "Lore elit. Cumque consequatur optio architecto voluptatibus nesciunt. Reiciendis?"
      }
      
    ]
}

